pyvoteview/__init__.py
pyvoteview/_url.py
pyvoteview/_utilities.py
pyvoteview/_validators.py
pyvoteview/core.py
pyvoteview-0.3.0.dist-info/licenses/LICENSE
pyvoteview-0.3.0.dist-info/METADATA
pyvoteview-0.3.0.dist-info/WHEEL
pyvoteview-0.3.0.dist-info/top_level.txt
pyvoteview-0.3.0.dist-info/RECORD
