Metadata-Version: 2.4
Name: pyvoteview
Version: 0.3.0
Summary: PyVoteview package to process VoteView site data.
Author-email: Jeremy Kazimer <jeremykazimer@gmail.com>
License-Expression: Apache-2.0
Project-URL: source, https://github.com/k-z-m-r/PyVoteview
Keywords: voteview,congress,politics
Classifier: Intended Audience :: Developers
Classifier: Intended Audience :: Science/Research
Classifier: Natural Language :: English
Classifier: Operating System :: OS Independent
Classifier: Programming Language :: Python
Classifier: Programming Language :: Python :: 3
Classifier: Programming Language :: Python :: 3.11
Classifier: Programming Language :: Python :: 3.12
Classifier: Programming Language :: Python :: 3.13
Requires-Python: >=3.11
License-File: LICENSE
Requires-Dist: polars[pandas,pyarrow]==1.33.1
Dynamic: license-file
